parsial/__init__.py
parsial/parsial.py
parsial-0.1.0.dist-info/LICENSE
parsial-0.1.0.dist-info/METADATA
parsial-0.1.0.dist-info/WHEEL
parsial-0.1.0.dist-info/top_level.txt
parsial-0.1.0.dist-info/RECORD
