Metadata-Version: 2.1
Name: parsial
Version: 0.1.0
Summary: Python library that transforms any string parser into a parser that skips portions of the input that contain syntax errors.
Author: Andrei Lapets
Author-email: a@lapets.io
License: MIT
Project-URL: Repository, https://github.com/reity/parsial
Project-URL: Documentation, https://parsial.readthedocs.io
Requires-Python: >=3.7
License-File: LICENSE
Provides-Extra: docs
Requires-Dist: toml~=0.10.2; extra == "docs"
Requires-Dist: sphinx~=5.0; extra == "docs"
Requires-Dist: sphinx-rtd-theme~=1.1.0; extra == "docs"
Provides-Extra: test
Requires-Dist: pytest~=7.4; extra == "test"
Requires-Dist: pytest-cov~=4.0; extra == "test"
Provides-Extra: lint
Requires-Dist: pylint~=2.17; extra == "lint"
Provides-Extra: coveralls
Requires-Dist: coveralls~=3.3.1; extra == "coveralls"
Provides-Extra: publish
Requires-Dist: build~=0.10; extra == "publish"
Requires-Dist: twine~=4.0; extra == "publish"
